VehicleDetectionTracker/VehicleDetectionTracker.py
VehicleDetectionTracker/__init__.py
VehicleDetectionTracker/color_classifier/__init__.py
VehicleDetectionTracker/color_classifier/classifier.py
VehicleDetectionTracker/color_classifier/color_classifier.py
VehicleDetectionTracker/color_classifier/config.py
VehicleDetectionTracker/data/color_labels.txt
VehicleDetectionTracker/data/model-weights-spectrico-car-colors-mobilenet-224x224-052EAC82.pb
VehicleDetectionTracker/data/model-weights-spectrico-mmr-mobilenet-128x128-344FF72B.pb
VehicleDetectionTracker/data/model_labels.txt
VehicleDetectionTracker/model_classifier/__init__.py
VehicleDetectionTracker/model_classifier/classifier.py
VehicleDetectionTracker/model_classifier/config.py
VehicleDetectionTracker-0.0.32.dist-info/LICENSE
VehicleDetectionTracker-0.0.32.dist-info/METADATA
VehicleDetectionTracker-0.0.32.dist-info/WHEEL
VehicleDetectionTracker-0.0.32.dist-info/top_level.txt
VehicleDetectionTracker-0.0.32.dist-info/RECORD
