Metadata-Version: 2.1
Name: VehicleDetectionTracker
Version: 0.0.32
Summary: VehicleDetectionTracker 🚗: Effortlessly track and detect vehicles in images and videos with advanced algorithms. 🚙🚕 Boost your computer vision project!" 🔍📹
Home-page: https://github.com/sergio11/vehicle_detection_tracker
Author: Sergio Sánchez Sánchez
Author-email: dreamsoftware92@gmail.com
Keywords: Vehicle tracking,Object detection,Computer vision,Video processing,Traffic analysis,Traffic management,Automated surveillance,Vehicle recognition,Video analysis,Machine learning
Classifier: Development Status :: 4 - Beta
Classifier: Intended Audience :: Developers
Classifier: License :: OSI Approved :: MIT License
Classifier: Programming Language :: Python :: 3
Classifier: Programming Language :: Python :: 3.7
Classifier: Programming Language :: Python :: 3.8
Classifier: Programming Language :: Python :: 3.9
Classifier: Programming Language :: Python :: 3.10
Requires-Python: >=3.7, <4
License-File: LICENSE
Requires-Dist: opencv-python ==4.8.1.78
Requires-Dist: imutils ==0.5.4
Requires-Dist: ultralytics ==8.0.145
Requires-Dist: tensorflow ==2.14.0
